{
    "nodes": [
        {
            "index": 0,
            "patterns": [
                0
            ],
            "chain": "A",
            "atomName": "O",
            "residueNumber": "1013",
            "residueName": "ASN",
            "isLigand": false,
            "atomType": "Acceptor",
            "color": "#7CB4BE",
            "atomTypeInt": "2"
        },
        {
            "index": 1,
            "patterns": [
                0
            ],
            "chain": "A",
            "atomName": "O",
            "residueNumber": "1011",
            "residueName": "GLU",
            "isLigand": false,
            "atomType": "Acceptor",
            "color": "#7CB4BE",
            "atomTypeInt": "2"
        },
        {
            "index": 2,
            "patterns": [
                0
            ],
            "chain": "B",
            "atomName": "NH1",
            "residueNumber": "26",
            "residueName": "ARG",
            "isLigand": true,
            "atomType": "Donor/Positive",
            "color": "#9BCE91",
            "atomTypeInt": "55"
        },
        {
            "index": 3,
            "patterns": [
                0
            ],
            "chain": "B",
            "atomName": "NH2",
            "residueNumber": "26",
            "residueName": "ARG",
            "isLigand": true,
            "atomType": "Donor/Positive",
            "color": "#9BCE91",
            "atomTypeInt": "55"
        }
    ],
    "links": [
        {
            "patterns": [
                0
            ],
            "source": 0,
            "target": 3,
            "interactionType": "Hydrogen bond",
            "distance": "2.744990016181371",
            "interactionTypeInt": "31"
        },
        {
            "patterns": [
                0
            ],
            "source": 0,
            "target": 2,
            "interactionType": "Hydrogen bond",
            "distance": "2.993104571993242",
            "interactionTypeInt": "31"
        },
        {
            "patterns": [
                0
            ],
            "source": 1,
            "target": 2,
            "interactionType": "Hydrogen bond",
            "distance": "2.6624481282089207",
            "interactionTypeInt": "31"
        }
    ]
}