{
    "nodes": [
        {
            "index": 0,
            "patterns": [],
            "chain": "A",
            "atomName": "OE2",
            "residueNumber": "99",
            "residueName": "GLU",
            "isLigand": false,
            "atomType": "Acceptor/Negative",
            "color": "#7CB4BE",
            "atomTypeInt": "26"
        },
        {
            "index": 1,
            "patterns": [],
            "chain": "A",
            "atomName": "NH2",
            "residueNumber": "33",
            "residueName": "ARG",
            "isLigand": false,
            "atomType": "Donor/Positive",
            "color": "#7CB4BE",
            "atomTypeInt": "55"
        },
        {
            "index": 2,
            "patterns": [],
            "chain": "A",
            "atomName": "NH1",
            "residueNumber": "33",
            "residueName": "ARG",
            "isLigand": false,
            "atomType": "Donor/Positive",
            "color": "#7CB4BE",
            "atomTypeInt": "55"
        },
        {
            "index": 3,
            "patterns": [],
            "chain": "B",
            "atomName": "OD1",
            "residueNumber": "118",
            "residueName": "ASP",
            "isLigand": true,
            "atomType": "Acceptor/Negative",
            "color": "#9BCE91",
            "atomTypeInt": "26"
        },
        {
            "index": 4,
            "patterns": [],
            "chain": "A",
            "atomName": "NE",
            "residueNumber": "33",
            "residueName": "ARG",
            "isLigand": false,
            "atomType": "Donor/Positive",
            "color": "#7CB4BE",
            "atomTypeInt": "55"
        },
        {
            "index": 5,
            "patterns": [],
            "chain": "A",
            "atomName": "OE1",
            "residueNumber": "99",
            "residueName": "GLU",
            "isLigand": false,
            "atomType": "Acceptor/Negative",
            "color": "#7CB4BE",
            "atomTypeInt": "26"
        },
        {
            "index": 6,
            "patterns": [],
            "chain": "B",
            "atomName": "OD2",
            "residueNumber": "118",
            "residueName": "ASP",
            "isLigand": true,
            "atomType": "Acceptor/Negative",
            "color": "#9BCE91",
            "atomTypeInt": "26"
        },
        {
            "index": 7,
            "patterns": [],
            "chain": "A",
            "atomName": "CZ",
            "residueNumber": "33",
            "residueName": "ARG",
            "isLigand": false,
            "atomType": "Positive",
            "color": "#7CB4BE",
            "atomTypeInt": "11"
        }
    ],
    "links": [
        {
            "patterns": [],
            "source": 0,
            "target": 6,
            "interactionType": "Repulsive",
            "distance": "5.185725255013702",
            "interactionTypeInt": "37"
        },
        {
            "patterns": [],
            "source": 1,
            "target": 3,
            "interactionType": "Hydrogen bond/Salt bridge",
            "distance": "2.713159159404459",
            "interactionTypeInt": "713"
        },
        {
            "patterns": [],
            "source": 1,
            "target": 6,
            "interactionType": "Salt bridge",
            "distance": "3.2708082178304427",
            "interactionTypeInt": "23"
        },
        {
            "patterns": [],
            "source": 2,
            "target": 3,
            "interactionType": "Hydrogen bond/Salt bridge",
            "distance": "2.7843047024026686",
            "interactionTypeInt": "713"
        },
        {
            "patterns": [],
            "source": 2,
            "target": 6,
            "interactionType": "Salt bridge",
            "distance": "3.130615937376391",
            "interactionTypeInt": "23"
        },
        {
            "patterns": [],
            "source": 4,
            "target": 3,
            "interactionType": "Salt bridge",
            "distance": "4.507936070402795",
            "interactionTypeInt": "23"
        },
        {
            "patterns": [],
            "source": 7,
            "target": 3,
            "interactionType": "Salt bridge",
            "distance": "3.198967844241944",
            "interactionTypeInt": "23"
        },
        {
            "patterns": [],
            "source": 5,
            "target": 3,
            "interactionType": "Repulsive",
            "distance": "5.362239824429147",
            "interactionTypeInt": "37"
        },
        {
            "patterns": [],
            "source": 4,
            "target": 6,
            "interactionType": "Salt bridge",
            "distance": "4.764340336810104",
            "interactionTypeInt": "23"
        },
        {
            "patterns": [],
            "source": 5,
            "target": 6,
            "interactionType": "Repulsive",
            "distance": "4.788567714557",
            "interactionTypeInt": "37"
        },
        {
            "patterns": [],
            "source": 7,
            "target": 6,
            "interactionType": "Salt bridge",
            "distance": "3.570307220846718",
            "interactionTypeInt": "23"
        }
    ]
}