{
	"nodes": [
		{
			"index": 0,
			"patterns": [
				0
			],
			"chain": "D",
			"atomName": "O",
			"residueNumber": "31",
			"residueName": "LEU",
			"isLigand": true,
			"atomType": "Acceptor",
			"color": "#9BCE91",
			"atomTypeInt": "2"
		},
		{
			"index": 1,
			"patterns": [
				0
			],
			"chain": "A",
			"atomName": "NE2",
			"residueNumber": "197",
			"residueName": "GLN",
			"isLigand": false,
			"atomType": "Donor",
			"color": "#7CB4BE",
			"atomTypeInt": "5"
		}
	],
	"links": [
		{
			"patterns": [
				0
			],
			"source": 1,
			"target": 0,
			"interactionType": "Hydrogen bond",
			"distance": "8.266179497078156",
			"interactionTypeInt": "29"
		}
	]
}