{
    "nodes": [
        {
            "index": 0,
            "patterns": [
                0
            ],
            "chain": "A",
            "atomName": "CG",
            "residueNumber": "191",
            "residueName": "PRO",
            "isLigand": false,
            "atomType": "Hydrophobic",
            "color": "#7CB4BE",
            "atomTypeInt": "7"
        },
        {
            "index": 1,
            "patterns": [
                0
            ],
            "chain": "A",
            "atomName": "CB",
            "residueNumber": "191",
            "residueName": "PRO",
            "isLigand": false,
            "atomType": "Hydrophobic",
            "color": "#7CB4BE",
            "atomTypeInt": "7"
        },
        {
            "index": 2,
            "patterns": [
                0
            ],
            "chain": "B",
            "atomName": "CG1",
            "residueNumber": "12",
            "residueName": "ILE",
            "isLigand": true,
            "atomType": "Hydrophobic",
            "color": "#9BCE91",
            "atomTypeInt": "7"
        },
        {
            "index": 3,
            "patterns": [
                0
            ],
            "chain": "B",
            "atomName": "CD1",
            "residueNumber": "12",
            "residueName": "ILE",
            "isLigand": true,
            "atomType": "Hydrophobic",
            "color": "#9BCE91",
            "atomTypeInt": "7"
        }
    ],
    "links": [
        {
            "patterns": [
                0
            ],
            "source": 0,
            "target": 3,
            "interactionType": "Hydrophobic",
            "distance": "3.7160525668531603",
            "interactionTypeInt": "29"
        },
        {
            "patterns": [
                0
            ],
            "source": 0,
            "target": 2,
            "interactionType": "Hydrophobic",
            "distance": "3.650199671867461",
            "interactionTypeInt": "29"
        },
        {
            "patterns": [
                0
            ],
            "source": 1,
            "target": 3,
            "interactionType": "Hydrophobic",
            "distance": "3.6861570959839067",
            "interactionTypeInt": "29"
        },
        {
            "patterns": [
                0
            ],
            "source": 1,
            "target": 2,
            "interactionType": "Hydrophobic",
            "distance": "3.7711166672727607",
            "interactionTypeInt": "29"
        }
    ]
}