{
    "nodes": [
        {
            "index": 0,
            "patterns": [],
            "chain": "B",
            "atomName": "CD1",
            "residueNumber": "62",
            "residueName": "PHE",
            "isLigand": true,
            "atomType": "Aromatic/Hydrophobic",
            "color": "#9BCE91",
            "atomTypeInt": "21"
        },
        {
            "index": 1,
            "patterns": [],
            "chain": "A",
            "atomName": "CZ3",
            "residueNumber": "500",
            "residueName": "TRP",
            "isLigand": false,
            "atomType": "Aromatic/Hydrophobic",
            "color": "#7CB4BE",
            "atomTypeInt": "21"
        },
        {
            "index": 2,
            "patterns": [],
            "chain": "B",
            "atomName": "CE1",
            "residueNumber": "62",
            "residueName": "PHE",
            "isLigand": true,
            "atomType": "Aromatic/Hydrophobic",
            "color": "#9BCE91",
            "atomTypeInt": "21"
        },
        {
            "index": 3,
            "patterns": [],
            "chain": "A",
            "atomName": "CE3",
            "residueNumber": "500",
            "residueName": "TRP",
            "isLigand": false,
            "atomType": "Aromatic/Hydrophobic",
            "color": "#7CB4BE",
            "atomTypeInt": "21"
        }
    ],
    "links": [
        {
            "patterns": [],
            "source": 1,
            "target": 0,
            "interactionType": "Hydrophobic",
            "distance": "3.7128843241908096",
            "interactionTypeInt": "29"
        },
        {
            "patterns": [],
            "source": 1,
            "target": 2,
            "interactionType": "Hydrophobic",
            "distance": "3.6753452043869963",
            "interactionTypeInt": "29"
        },
        {
            "patterns": [],
            "source": 3,
            "target": 2,
            "interactionType": "Hydrophobic",
            "distance": "3.7010481634988857",
            "interactionTypeInt": "29"
        }
    ]
}