{
	"nodes": [
		{
			"index": 0,
			"patterns": [
				0,
				1
			],
			"chain": "I",
			"atomName": "CZ",
			"residueNumber": "4",
			"residueName": "ARG",
			"isLigand": true,
			"atomType": "Positive",
			"color": "#9BCE91",
			"atomTypeInt": "11"
		},
		{
			"index": 1,
			"patterns": [
				0,
				1
			],
			"chain": "E",
			"atomName": "OD2",
			"residueNumber": "189",
			"residueName": "ASP",
			"isLigand": false,
			"atomType": "Acceptor/Negative",
			"color": "#7CB4BE",
			"atomTypeInt": "26"
		},
		{
			"index": 2,
			"patterns": [
				0,
				1
			],
			"chain": "E",
			"atomName": "O",
			"residueNumber": "219",
			"residueName": "GLY",
			"isLigand": false,
			"atomType": "Acceptor",
			"color": "#7CB4BE",
			"atomTypeInt": "2"
		},
		{
			"index": 3,
			"patterns": [
				0,
				1
			],
			"chain": "I",
			"atomName": "NH2",
			"residueNumber": "4",
			"residueName": "ARG",
			"isLigand": true,
			"atomType": "Donor/Positive",
			"color": "#9BCE91",
			"atomTypeInt": "55"
		},
		{
			"index": 4,
			"patterns": [
				0,
				1
			],
			"chain": "E",
			"atomName": "OD1",
			"residueNumber": "189",
			"residueName": "ASP",
			"isLigand": false,
			"atomType": "Acceptor/Negative",
			"color": "#7CB4BE",
			"atomTypeInt": "26"
		},
		{
			"index": 5,
			"patterns": [
				0,
				1
			],
			"chain": "E",
			"atomName": "OG",
			"residueNumber": "190",
			"residueName": "SER",
			"isLigand": false,
			"atomType": "Acceptor/Donor",
			"color": "#7CB4BE",
			"atomTypeInt": "10"
		},
		{
			"index": 6,
			"patterns": [
				0,
				1
			],
			"chain": "I",
			"atomName": "NH1",
			"residueNumber": "4",
			"residueName": "ARG",
			"isLigand": true,
			"atomType": "Donor/Positive",
			"color": "#9BCE91",
			"atomTypeInt": "55"
		},
		{
			"index": 7,
			"patterns": [
				0,
				1
			],
			"chain": "I",
			"atomName": "NE",
			"residueNumber": "4",
			"residueName": "ARG",
			"isLigand": true,
			"atomType": "Donor/Positive",
			"color": "#9BCE91",
			"atomTypeInt": "55"
		}
	],
	"links": [
		{
			"patterns": [
				0,
				1
			],
			"source": 4,
			"target": 0,
			"interactionType": "Salt bridge",
			"distance": "13.61270074811182",
			"interactionTypeInt": "19"
		},
		{
			"patterns": [
				0,
				1
			],
			"source": 1,
			"target": 0,
			"interactionType": "Salt bridge",
			"distance": "12.259213897414156",
			"interactionTypeInt": "19"
		},
		{
			"patterns": [
				0,
				1
			],
			"source": 1,
			"target": 7,
			"interactionType": "Salt bridge",
			"distance": "22.22947827016469",
			"interactionTypeInt": "19"
		},
		{
			"patterns": [
				0,
				1
			],
			"source": 1,
			"target": 3,
			"interactionType": "Hydrogen bond/Salt bridge",
			"distance": "7.690776643925346",
			"interactionTypeInt": "551"
		},
		{
			"patterns": [
				0,
				1
			],
			"source": 1,
			"target": 6,
			"interactionType": "Salt bridge",
			"distance": "11.575836650590645",
			"interactionTypeInt": "19"
		},
		{
			"patterns": [
				0,
				1
			],
			"source": 2,
			"target": 3,
			"interactionType": "Hydrogen bond",
			"distance": "8.398669025758863",
			"interactionTypeInt": "29"
		},
		{
			"patterns": [
				0,
				1
			],
			"source": 4,
			"target": 3,
			"interactionType": "Salt bridge",
			"distance": "13.784850747397286",
			"interactionTypeInt": "19"
		},
		{
			"patterns": [
				0,
				1
			],
			"source": 4,
			"target": 7,
			"interactionType": "Salt bridge",
			"distance": "24.29278940144286",
			"interactionTypeInt": "19"
		},
		{
			"patterns": [
				0,
				1
			],
			"source": 4,
			"target": 6,
			"interactionType": "Hydrogen bond/Salt bridge",
			"distance": "7.8360384563711705",
			"interactionTypeInt": "551"
		},
		{
			"patterns": [
				0,
				1
			],
			"source": 5,
			"target": 6,
			"interactionType": "Hydrogen bond",
			"distance": "7.945627952052746",
			"interactionTypeInt": "29"
		}
	]
}