{
    "nodes": [
        {
            "index": 0,
            "patterns": [
                0
            ],
            "chain": "B",
            "atomName": "OE2",
            "residueNumber": "61",
            "residueName": "GLU",
            "isLigand": true,
            "atomType": "Acceptor/Negative",
            "color": "#9BCE91",
            "atomTypeInt": "26"
        },
        {
            "index": 1,
            "patterns": [
                0
            ],
            "chain": "A",
            "atomName": "NE",
            "residueNumber": "54",
            "residueName": "ARG",
            "isLigand": false,
            "atomType": "Donor/Positive",
            "color": "#7CB4BE",
            "atomTypeInt": "55"
        }
    ],
    "links": [
        {
            "patterns": [
                0
            ],
            "source": 1,
            "target": 0,
            "interactionType": "Salt bridge",
            "distance": "5.768163388153019",
            "interactionTypeInt": "23"
        }
    ]
}