{
	"nodes": [
		{
			"index": 0,
			"patterns": [],
			"chain": "B",
			"atomName": "NH1",
			"residueNumber": "565",
			"residueName": "ARG",
			"isLigand": true,
			"atomType": "Donor/Positive",
			"color": "#9BCE91",
			"atomTypeInt": "55"
		},
		{
			"index": 1,
			"patterns": [],
			"chain": "A",
			"atomName": "NE2",
			"residueNumber": "40",
			"residueName": "HIS",
			"isLigand": false,
			"atomType": "Acceptor/Aromatic/Donor/Positive",
			"color": "#7CB4BE",
			"atomTypeInt": "330"
		}
	],
	"links": [
		{
			"patterns": [],
			"source": 1,
			"target": 0,
			"interactionType": "Repulsive",
			"distance": "34.45681310302825",
			"interactionTypeInt": "31"
		}
	]
}