{
    "nodes": [
        {
            "index": 0,
            "patterns": [],
            "chain": "B",
            "atomName": "CD2",
            "residueNumber": "62",
            "residueName": "PHE",
            "isLigand": true,
            "atomType": "Aromatic/Hydrophobic",
            "color": "#9BCE91",
            "atomTypeInt": "21"
        },
        {
            "index": 1,
            "patterns": [],
            "chain": "A",
            "atomName": "CD2",
            "residueNumber": "781",
            "residueName": "HIS",
            "isLigand": false,
            "atomType": "Aromatic",
            "color": "#7CB4BE",
            "atomTypeInt": "3"
        },
        {
            "index": 2,
            "patterns": [],
            "chain": "B",
            "atomName": "CD1",
            "residueNumber": "62",
            "residueName": "PHE",
            "isLigand": true,
            "atomType": "Aromatic/Hydrophobic",
            "color": "#9BCE91",
            "atomTypeInt": "21"
        },
        {
            "index": 3,
            "patterns": [],
            "chain": "B",
            "atomName": "CZ",
            "residueNumber": "62",
            "residueName": "PHE",
            "isLigand": true,
            "atomType": "Aromatic/Hydrophobic",
            "color": "#9BCE91",
            "atomTypeInt": "21"
        },
        {
            "index": 4,
            "patterns": [],
            "chain": "A",
            "atomName": "CE1",
            "residueNumber": "781",
            "residueName": "HIS",
            "isLigand": false,
            "atomType": "Aromatic",
            "color": "#7CB4BE",
            "atomTypeInt": "3"
        },
        {
            "index": 5,
            "patterns": [],
            "chain": "A",
            "atomName": "NE2",
            "residueNumber": "781",
            "residueName": "HIS",
            "isLigand": false,
            "atomType": "Acceptor/Aromatic/Donor/Positive",
            "color": "#7CB4BE",
            "atomTypeInt": "330"
        },
        {
            "index": 6,
            "patterns": [],
            "chain": "B",
            "atomName": "CG",
            "residueNumber": "62",
            "residueName": "PHE",
            "isLigand": true,
            "atomType": "Aromatic/Hydrophobic",
            "color": "#9BCE91",
            "atomTypeInt": "21"
        },
        {
            "index": 7,
            "patterns": [],
            "chain": "B",
            "atomName": "CE1",
            "residueNumber": "62",
            "residueName": "PHE",
            "isLigand": true,
            "atomType": "Aromatic/Hydrophobic",
            "color": "#9BCE91",
            "atomTypeInt": "21"
        }
    ],
    "links": [
        {
            "patterns": [],
            "source": 4,
            "target": 0,
            "interactionType": "Aromatic",
            "distance": "3.4829530265953497",
            "interactionTypeInt": "19"
        },
        {
            "patterns": [],
            "source": 1,
            "target": 2,
            "interactionType": "Aromatic",
            "distance": "3.201237500266357",
            "interactionTypeInt": "19"
        },
        {
            "patterns": [],
            "source": 1,
            "target": 7,
            "interactionType": "Aromatic",
            "distance": "3.318260455201666",
            "interactionTypeInt": "19"
        },
        {
            "patterns": [],
            "source": 5,
            "target": 2,
            "interactionType": "Aromatic",
            "distance": "3.1344476166432798",
            "interactionTypeInt": "19"
        },
        {
            "patterns": [],
            "source": 5,
            "target": 3,
            "interactionType": "Aromatic",
            "distance": "3.4360825609007315",
            "interactionTypeInt": "19"
        },
        {
            "patterns": [],
            "source": 4,
            "target": 6,
            "interactionType": "Aromatic",
            "distance": "3.1939220011557303",
            "interactionTypeInt": "19"
        },
        {
            "patterns": [],
            "source": 5,
            "target": 6,
            "interactionType": "Aromatic",
            "distance": "3.2743957594972355",
            "interactionTypeInt": "19"
        },
        {
            "patterns": [],
            "source": 5,
            "target": 7,
            "interactionType": "Aromatic",
            "distance": "3.1928391209318936",
            "interactionTypeInt": "19"
        }
    ]
}