{
	"nodes": [
		{
			"index": 0,
			"patterns": [
				0
			],
			"chain": "A",
			"atomName": "N",
			"residueNumber": "87",
			"residueName": "GLY",
			"isLigand": false,
			"atomType": "Donor",
			"color": "#7CB4BE",
			"atomTypeInt": "5"
		},
		{
			"index": 1,
			"patterns": [
				0
			],
			"chain": "B",
			"atomName": "OD1",
			"residueNumber": "18",
			"residueName": "ASN",
			"isLigand": true,
			"atomType": "Acceptor",
			"color": "#9BCE91",
			"atomTypeInt": "2"
		}
	],
	"links": [
		{
			"patterns": [
				0
			],
			"source": 0,
			"target": 1,
			"interactionType": "Hydrogen bond",
			"distance": "8.616784433212388",
			"interactionTypeInt": "29"
		}
	]
}