{
    "nodes": [
        {
            "index": 0,
            "patterns": [
                0
            ],
            "chain": "B",
            "atomName": "CE2",
            "residueNumber": "38",
            "residueName": "PHE",
            "isLigand": true,
            "atomType": "Aromatic/Hydrophobic",
            "color": "#9BCE91",
            "atomTypeInt": "21"
        },
        {
            "index": 1,
            "patterns": [
                0
            ],
            "chain": "B",
            "atomName": "CD2",
            "residueNumber": "38",
            "residueName": "PHE",
            "isLigand": true,
            "atomType": "Aromatic/Hydrophobic",
            "color": "#9BCE91",
            "atomTypeInt": "21"
        },
        {
            "index": 2,
            "patterns": [
                0
            ],
            "chain": "B",
            "atomName": "CG",
            "residueNumber": "38",
            "residueName": "PHE",
            "isLigand": true,
            "atomType": "Aromatic/Hydrophobic",
            "color": "#9BCE91",
            "atomTypeInt": "21"
        },
        {
            "index": 3,
            "patterns": [
                0
            ],
            "chain": "A",
            "atomName": "CG2",
            "residueNumber": "413",
            "residueName": "VAL",
            "isLigand": false,
            "atomType": "Hydrophobic",
            "color": "#7CB4BE",
            "atomTypeInt": "7"
        }
    ],
    "links": [
        {
            "patterns": [
                0
            ],
            "source": 3,
            "target": 0,
            "interactionType": "Hydrophobic",
            "distance": "3.6988431615198722",
            "interactionTypeInt": "29"
        },
        {
            "patterns": [
                0
            ],
            "source": 3,
            "target": 1,
            "interactionType": "Hydrophobic",
            "distance": "3.219247458998949",
            "interactionTypeInt": "29"
        },
        {
            "patterns": [
                0
            ],
            "source": 3,
            "target": 2,
            "interactionType": "Hydrophobic",
            "distance": "3.722993721003171",
            "interactionTypeInt": "29"
        }
    ]
}