{
    "nodes": [
        {
            "index": 0,
            "patterns": [],
            "chain": "A",
            "atomName": "O",
            "residueNumber": "548",
            "residueName": "ARG",
            "isLigand": false,
            "atomType": "Acceptor",
            "color": "#7CB4BE",
            "atomTypeInt": "2"
        },
        {
            "index": 1,
            "patterns": [],
            "chain": "B",
            "atomName": "NZ",
            "residueNumber": "13",
            "residueName": "LYS",
            "isLigand": true,
            "atomType": "Donor/Positive",
            "color": "#9BCE91",
            "atomTypeInt": "55"
        }
    ],
    "links": [
        {
            "patterns": [],
            "source": 0,
            "target": 1,
            "interactionType": "Hydrogen bond",
            "distance": "2.7028123882108943",
            "interactionTypeInt": "31"
        }
    ]
}